{"title":"周颂·臣工之什","uid":"9c1dd16e80e84a181bb1848a22087e75","slug":"ZhouSong_ChenGongZhiShen","date":"2022-07-23T00:00:00.000Z","updated":"2022-08-02T05:42:16.000Z","comments":true,"path":"api/articles/ZhouSong_ChenGongZhiShen.json","keywords":null,"cover":"https://images.pexels.com/photos/880675/pexels-photo-880675.jpeg?auto=compress&cs=tinysrgb&w=1260&h=750&dpr=1","content":"<h3 id=\"《臣工》\"><a href=\"#《臣工》\" class=\"headerlink\" title=\"《臣工》\"></a>《臣工》</h3><p>嗟嗟臣工，敬尔在公。王厘尔成，來咨來茹。嗟嗟保介，维莫之春。</p>\n<p>亦又何求？如何新畬？於皇來牟，將受厥明。</p>\n<p>明昭上帝，迄用康年。命我眾人，庤乃錢镈，奄觀铚艾。</p>\n<h3 id=\"《噫嘻》\"><a href=\"#《噫嘻》\" class=\"headerlink\" title=\"《噫嘻》\"></a>《噫嘻》</h3><p>噫嘻成王，既昭假尔。率时農夫，播厥百穀。</p>\n<p>駿发尔私，終三十里。亦服尔耕，十千维耦。</p>\n<h3 id=\"《振鷺》\"><a href=\"#《振鷺》\" class=\"headerlink\" title=\"《振鷺》\"></a>《振鷺》</h3><p>振鷺于飞，于彼西雍。我客戾止，亦有斯容。</p>\n<p>在彼无惡，在此无斁。庶幾夙夜，以永終譽。</p>\n<h3 id=\"《丰年》\"><a href=\"#《丰年》\" class=\"headerlink\" title=\"《丰年》\"></a>《丰年》</h3><p>丰年多黍多稌，亦有高廩，万億及秭。</p>\n<p>为酒为醴，烝畀祖妣，以洽百禮。降福孔皆。</p>\n<h3 id=\"《有瞽》\"><a href=\"#《有瞽》\" class=\"headerlink\" title=\"《有瞽》\"></a>《有瞽》</h3><p>有瞽有瞽，在周之庭。設業設虡，崇牙樹羽，应田縣鼓，鞉磬柷圉。</p>\n<p>既備乃奏，簫管備舉。喤喤厥声，肅雍和鳴，先祖是聽。我客戾止，永觀厥成。</p>\n<h3 id=\"《潛》\"><a href=\"#《潛》\" class=\"headerlink\" title=\"《潛》\"></a>《潛》</h3><p>猗与漆沮，潛有多鱼。</p>\n<p>有鳣有鮪，鰷鲿鰋鯉。</p>\n<p>以享以祀，以介景福。</p>\n<h3 id=\"《雍》\"><a href=\"#《雍》\" class=\"headerlink\" title=\"《雍》\"></a>《雍》</h3><p>有來雍雍，至止肅肅。相维辟公，天子穆穆。於薦廣牡，相予肆祀。假哉皇考，綏予孝子。</p>\n<p>宣哲维人，文武维後。燕及皇天，克昌厥後。綏我眉寿，介以繁祉。既右烈考，亦右文母。</p>\n<h3 id=\"《载见》\"><a href=\"#《载见》\" class=\"headerlink\" title=\"《载见》\"></a>《载见》</h3><p>载见辟王，曰求厥章。龙旗陽陽，和鈴央央，鞗革有鸧，休有烈光。</p>\n<p>率见昭考，以孝以享，以介眉寿。永言保之，思皇多祜。烈文辟公，綏以多福，俾緝熙于純嘏。</p>\n<h3 id=\"《有客》\"><a href=\"#《有客》\" class=\"headerlink\" title=\"《有客》\"></a>《有客》</h3><p>有客有客，亦白其马。有萋有且，敦琢其旅。</p>\n<p>有客宿宿，有客信信。言授之縶，以縶其马。</p>\n<p>薄言追之，左右綏之。既有淫威，降福孔夷。</p>\n<h3 id=\"《武》\"><a href=\"#《武》\" class=\"headerlink\" title=\"《武》\"></a>《武》</h3><p>於皇武王，无競维烈。</p>\n<p>允文文王，克開厥後。</p>\n<p>嗣武受之，勝殷遏刘，耆定尔功。</p>\n","text":"《臣工》嗟嗟臣工，敬尔在公。王厘尔成，來咨來茹。嗟嗟保介，维莫之春。 亦又何求？如何新畬？於皇來牟，將受厥明。 明昭上帝，迄用康年。命我眾人，庤乃錢镈，奄觀铚艾。 《噫嘻》噫嘻成王，既昭假尔。率时農夫，播厥百穀。 駿发尔私，終三十里。亦服尔耕，十千维耦。 《振鷺》振鷺于飞，于彼西...","link":"","photos":[],"count_time":{"symbolsCount":595,"symbolsTime":"1 mins."},"categories":[{"name":"周颂","slug":"周颂","count":3,"path":"api/categories/周颂.json"}],"tags":[{"name":"诗经","slug":"诗经","count":30,"path":"api/tags/诗经.json"},{"name":"周颂","slug":"周颂","count":3,"path":"api/tags/周颂.json"}],"toc":"<ol class=\"toc\"><li class=\"toc-item toc-level-3\"><a class=\"toc-link\" href=\"#%E3%80%8A%E8%87%A3%E5%B7%A5%E3%80%8B\"><span class=\"toc-text\">《臣工》</span></a></li><li class=\"toc-item toc-level-3\"><a class=\"toc-link\" href=\"#%E3%80%8A%E5%99%AB%E5%98%BB%E3%80%8B\"><span class=\"toc-text\">《噫嘻》</span></a></li><li class=\"toc-item toc-level-3\"><a class=\"toc-link\" href=\"#%E3%80%8A%E6%8C%AF%E9%B7%BA%E3%80%8B\"><span class=\"toc-text\">《振鷺》</span></a></li><li class=\"toc-item toc-level-3\"><a class=\"toc-link\" href=\"#%E3%80%8A%E4%B8%B0%E5%B9%B4%E3%80%8B\"><span class=\"toc-text\">《丰年》</span></a></li><li class=\"toc-item toc-level-3\"><a class=\"toc-link\" href=\"#%E3%80%8A%E6%9C%89%E7%9E%BD%E3%80%8B\"><span class=\"toc-text\">《有瞽》</span></a></li><li class=\"toc-item toc-level-3\"><a class=\"toc-link\" href=\"#%E3%80%8A%E6%BD%9B%E3%80%8B\"><span class=\"toc-text\">《潛》</span></a></li><li class=\"toc-item toc-level-3\"><a class=\"toc-link\" href=\"#%E3%80%8A%E9%9B%8D%E3%80%8B\"><span class=\"toc-text\">《雍》</span></a></li><li class=\"toc-item toc-level-3\"><a class=\"toc-link\" href=\"#%E3%80%8A%E8%BD%BD%E8%A7%81%E3%80%8B\"><span class=\"toc-text\">《载见》</span></a></li><li class=\"toc-item toc-level-3\"><a class=\"toc-link\" href=\"#%E3%80%8A%E6%9C%89%E5%AE%A2%E3%80%8B\"><span class=\"toc-text\">《有客》</span></a></li><li class=\"toc-item toc-level-3\"><a class=\"toc-link\" href=\"#%E3%80%8A%E6%AD%A6%E3%80%8B\"><span class=\"toc-text\">《武》</span></a></li></ol>","author":{"name":"森立设计","slug":"blog-author","avatar":"https://s3.bmp.ovh/imgs/2022/08/24/745a612bca277e56.png","link":"/","description":"LIFE AND DREAM","socials":{"github":"https://github.com/META-HY","twitter":"","stackoverflow":"","wechat":"","qq":"","weibo":"","zhihu":"","csdn":"","juejin":"","customs":{}}},"mapped":true,"prev_post":{"title":"周颂·闵予小子之什","uid":"e0773f0de3df425c3e65903b955bfdaf","slug":"ZhouSong_MinYuXiaoZiZhiShen","date":"2022-07-24T00:00:00.000Z","updated":"2022-08-02T05:42:24.000Z","comments":true,"path":"api/articles/ZhouSong_MinYuXiaoZiZhiShen.json","keywords":null,"cover":"https://images.pexels.com/photos/1310755/pexels-photo-1310755.jpeg?auto=compress&cs=tinysrgb&w=1600","text":"《闵予小子》闵予小子，遭家不造，嬛嬛在疚。於乎皇考！永世克孝。 念茲皇祖，陟降庭止。维予小子，夙夜敬止。於乎皇王！继序思不忘。 《访落》访予落止，率时昭考。於乎悠哉！朕未有艾，將予就之，继猶判渙。 维予小子，未堪家多难。紹庭上下，陟降厥家。休矣皇考，以保明其身。 《敬之》敬之敬之...","link":"","photos":[],"count_time":{"symbolsCount":756,"symbolsTime":"1 mins."},"categories":[{"name":"周颂","slug":"周颂","count":3,"path":"api/categories/周颂.json"}],"tags":[{"name":"诗经","slug":"诗经","count":30,"path":"api/tags/诗经.json"},{"name":"周颂","slug":"周颂","count":3,"path":"api/tags/周颂.json"}],"author":{"name":"森立设计","slug":"blog-author","avatar":"https://s3.bmp.ovh/imgs/2022/08/24/745a612bca277e56.png","link":"/","description":"LIFE AND DREAM","socials":{"github":"https://github.com/META-HY","twitter":"","stackoverflow":"","wechat":"","qq":"","weibo":"","zhihu":"","csdn":"","juejin":"","customs":{}}}},"next_post":{"title":"大雅·文王之什","uid":"c84bfb9c43a6d11f41c6175affd24590","slug":"DaYa_WenWangZhiShen","date":"2022-07-22T03:00:00.000Z","updated":"2022-08-02T05:44:13.000Z","comments":true,"path":"api/articles/DaYa_WenWangZhiShen.json","keywords":null,"cover":"https://images.pexels.com/photos/1102912/pexels-photo-1102912.jpeg?auto=compress&cs=tinysrgb&w=1600","text":"《文王》文王在上，於昭于天，周虽旧邦，其命维新。 有周不显，帝命不时。文王陟降，在帝左右。 亹亹文王，令聞不已。陳錫哉周，侯文王孙子。 文王孙子，本支百世。凡周之士，不显亦世。 世之不显，厥猶翼翼。思皇多士，生此王国。 王国克生，维周之楨。济济多士，文王以寧。 穆穆文王，於緝熙敬...","link":"","photos":[],"count_time":{"symbolsCount":"2.2k","symbolsTime":"2 mins."},"categories":[{"name":"大雅","slug":"大雅","count":3,"path":"api/categories/大雅.json"}],"tags":[{"name":"诗经","slug":"诗经","count":30,"path":"api/tags/诗经.json"},{"name":"大雅","slug":"大雅","count":3,"path":"api/tags/大雅.json"}],"author":{"name":"森立设计","slug":"blog-author","avatar":"https://s3.bmp.ovh/imgs/2022/08/24/745a612bca277e56.png","link":"/","description":"LIFE AND DREAM","socials":{"github":"https://github.com/META-HY","twitter":"","stackoverflow":"","wechat":"","qq":"","weibo":"","zhihu":"","csdn":"","juejin":"","customs":{}}}}}