{"name":"周颂","slug":"周颂","count":3,"postlist":[{"title":"周颂·闵予小子之什","uid":"e0773f0de3df425c3e65903b955bfdaf","slug":"ZhouSong_MinYuXiaoZiZhiShen","date":"2022-07-24T00:00:00.000Z","updated":"2022-08-02T05:42:24.000Z","comments":true,"path":"api/articles/ZhouSong_MinYuXiaoZiZhiShen.json","keywords":null,"cover":"https://images.pexels.com/photos/1310755/pexels-photo-1310755.jpeg?auto=compress&cs=tinysrgb&w=1600","text":"《闵予小子》闵予小子，遭家不造，嬛嬛在疚。於乎皇考！永世克孝。 念茲皇祖，陟降庭止。维予小子，夙夜敬止。於乎皇王！继序思不忘。 《访落》访予落止，率时昭考。於乎悠哉！朕未有艾，將予就之，继猶判渙。 维予小子，未堪家多难。紹庭上下，陟降厥家。休矣皇考，以保明其身。 《敬之》敬之敬之...","link":"","photos":[],"count_time":{"symbolsCount":756,"symbolsTime":"1 mins."},"categories":[{"name":"周颂","slug":"周颂","count":3,"path":"api/categories/周颂.json"}],"tags":[{"name":"诗经","slug":"诗经","count":30,"path":"api/tags/诗经.json"},{"name":"周颂","slug":"周颂","count":3,"path":"api/tags/周颂.json"}],"author":{"name":"森立设计","slug":"blog-author","avatar":"https://s3.bmp.ovh/imgs/2022/08/24/745a612bca277e56.png","link":"/","description":"LIFE AND DREAM","socials":{"github":"https://github.com/META-HY","twitter":"","stackoverflow":"","wechat":"","qq":"","weibo":"","zhihu":"","csdn":"","juejin":"","customs":{}}}},{"title":"周颂·臣工之什","uid":"9c1dd16e80e84a181bb1848a22087e75","slug":"ZhouSong_ChenGongZhiShen","date":"2022-07-23T00:00:00.000Z","updated":"2022-08-02T05:42:16.000Z","comments":true,"path":"api/articles/ZhouSong_ChenGongZhiShen.json","keywords":null,"cover":"https://images.pexels.com/photos/880675/pexels-photo-880675.jpeg?auto=compress&cs=tinysrgb&w=1260&h=750&dpr=1","text":"《臣工》嗟嗟臣工，敬尔在公。王厘尔成，來咨來茹。嗟嗟保介，维莫之春。 亦又何求？如何新畬？於皇來牟，將受厥明。 明昭上帝，迄用康年。命我眾人，庤乃錢镈，奄觀铚艾。 《噫嘻》噫嘻成王，既昭假尔。率时農夫，播厥百穀。 駿发尔私，終三十里。亦服尔耕，十千维耦。 《振鷺》振鷺于飞，于彼西...","link":"","photos":[],"count_time":{"symbolsCount":595,"symbolsTime":"1 mins."},"categories":[{"name":"周颂","slug":"周颂","count":3,"path":"api/categories/周颂.json"}],"tags":[{"name":"诗经","slug":"诗经","count":30,"path":"api/tags/诗经.json"},{"name":"周颂","slug":"周颂","count":3,"path":"api/tags/周颂.json"}],"author":{"name":"森立设计","slug":"blog-author","avatar":"https://s3.bmp.ovh/imgs/2022/08/24/745a612bca277e56.png","link":"/","description":"LIFE AND DREAM","socials":{"github":"https://github.com/META-HY","twitter":"","stackoverflow":"","wechat":"","qq":"","weibo":"","zhihu":"","csdn":"","juejin":"","customs":{}}}},{"title":"周颂·清庙之什","uid":"eb4ce34878e9f1393418f4eed40b2149","slug":"ZhouSong_QingMiaoZhiShen","date":"2022-07-25T00:00:00.000Z","updated":"2022-08-02T05:42:31.000Z","comments":true,"path":"api/articles/ZhouSong_QingMiaoZhiShen.json","keywords":null,"cover":"https://images.pexels.com/photos/748626/pexels-photo-748626.jpeg?auto=compress&cs=tinysrgb&w=1260&h=750&dpr=1","text":"《清庙》於穆清庙，肅雍显相。 济济多士，秉文之德。 對越在天，駿奔走在庙。 不显不承？无射於人斯。 《维天之命》维天之命，於穆不已。 於乎不显！文王之德之純。 假以溢我，我其收之。 駿惠我文王，曾孙篤之。 《维清》维清緝熙，文王之典。肇禋，迄用有成，维周之禎。 《烈文》烈文辟公，...","link":"","photos":[],"count_time":{"symbolsCount":578,"symbolsTime":"1 mins."},"categories":[{"name":"周颂","slug":"周颂","count":3,"path":"api/categories/周颂.json"}],"tags":[{"name":"诗经","slug":"诗经","count":30,"path":"api/tags/诗经.json"},{"name":"周颂","slug":"周颂","count":3,"path":"api/tags/周颂.json"}],"author":{"name":"森立设计","slug":"blog-author","avatar":"https://s3.bmp.ovh/imgs/2022/08/24/745a612bca277e56.png","link":"/","description":"LIFE AND DREAM","socials":{"github":"https://github.com/META-HY","twitter":"","stackoverflow":"","wechat":"","qq":"","weibo":"","zhihu":"","csdn":"","juejin":"","customs":{}}}}]}